{"cameraMode":{"drawMode":0,"name":"Shaded","section":"Shading Mode"},"sceneLighting":true,"audioPlay":false,"sceneViewState":{"showFog":true,"showMaterialUpdate":false,"showSkybox":true,"showFlares":true,"showImageEffects":true,"showParticleSystems":true},"in2DMode":false,"pivot":{"x":68.60464477539063,"y":-52.497615814208987,"z":119.38188934326172},"rotation":{"x":0.27405890822410586,"y":0.03604864329099655,"z":-0.01028089877218008,"w":0.9609897136688232},"size":171.91415405273438,"orthographic":false}